numberguess/__init__.py
numberguess/numberguess.py
numberguess-0.1.dist-info/DESCRIPTION.rst
numberguess-0.1.dist-info/METADATA
numberguess-0.1.dist-info/RECORD
numberguess-0.1.dist-info/WHEEL
numberguess-0.1.dist-info/metadata.json
numberguess-0.1.dist-info/top_level.txt
