Metadata-Version: 2.0
Name: numberguess
Version: 0.1
Summary: number guessing game
Home-page: https://github.com/austinperryfrancis/numberguess
Author: austinperryfrancis
Author-email: austin.francis@aggiemail.usu.edu
License: UNKNOWN
Platform: UNKNOWN
